predictions/__init__.py
predictions/crash.py
predictions/mines.py
predictions/roulette.py
predictions/towers.py
predictions-1.0.2.dist-info/LICENSE
predictions-1.0.2.dist-info/METADATA
predictions-1.0.2.dist-info/WHEEL
predictions-1.0.2.dist-info/top_level.txt
predictions-1.0.2.dist-info/RECORD
