Metadata-Version: 2.1
Name: predictions
Version: 1.0.2
Summary: A package that predicts bloxflip games
Home-page: UNKNOWN
Author: DuxV2
Author-email: duxv420@gmail.com
License: UNKNOWN
Keywords: python,bloxflip,bloxflippredictor,predictor
Platform: UNKNOWN
Classifier: Development Status :: 1 - Planning
Classifier: Intended Audience :: Developers
Classifier: Programming Language :: Python :: 3
Classifier: Operating System :: Unix
Classifier: Operating System :: MacOS :: MacOS X
Classifier: Operating System :: Microsoft :: Windows
License-File: LICENSE
Requires-Dist: cloudscraper
